iteroo/it.py
iteroo-0.0.1.dist-info/METADATA
iteroo-0.0.1.dist-info/WHEEL
iteroo-0.0.1.dist-info/licenses/LICENSE
iteroo-0.0.1.dist-info/RECORD
