Metadata-Version: 2.4
Name: iteroo
Version: 0.0.1
Summary: Object orientated iterator wrapper.
Project-URL: Homepage, https://github.com/cburbridge/iteroo
Project-URL: Bug Reports, https://github.com/cburbridge/iteroo/issues
Project-URL: Source, https://github.com/cburbridge/iteroo
Author-email: Chris Burbridge <cburbridge@gmail.com>
Maintainer-email: Chris Burbridge <cburbridge@gmail.com>
License: MIT
License-File: LICENSE
Keywords: functional,iterators
Classifier: Development Status :: 3 - Alpha
Classifier: Intended Audience :: Developers
Classifier: License :: OSI Approved :: MIT License
Classifier: Programming Language :: Python :: 3
Classifier: Programming Language :: Python :: 3 :: Only
Classifier: Programming Language :: Python :: 3.8
Classifier: Programming Language :: Python :: 3.9
Classifier: Programming Language :: Python :: 3.10
Classifier: Programming Language :: Python :: 3.11
Classifier: Programming Language :: Python :: 3.12
Classifier: Topic :: Software Development :: Libraries
Requires-Python: >=3.8
Provides-Extra: test
Requires-Dist: pytest; extra == 'test'
Requires-Dist: pytest-cov; extra == 'test'
